build/lib/clean_gml/__init__.py
build/lib/clean_gml/datatype_changes.py
build/lib/clean_gml/find_meta.py
build/lib/clean_gml/namespace.py
build/lib/clean_gml/gml/__init__.py
build/lib/clean_gml/gml/gml.py
build/lib/clean_gml/gml/gml_base.py
build/lib/clean_gml/gml/gml_schema.py
build/lib/clean_gml/utils/__init__.py
build/lib/clean_gml/utils/abs_path.py
build/lib/clean_gml/utils/file_operations.py
build/lib/clean_gml/utils/yml2dict.py
build/lib/examples/__init__.py
build/lib/examples/example_read.py
clean_gml/__init__.py
clean_gml/datatype_changes.py
clean_gml/find_meta.py
clean_gml/namespace.py
clean_gml/gml/__init__.py
clean_gml/gml/gml.py
clean_gml/gml/gml_base.py
clean_gml/gml/gml_schema.py
clean_gml/utils/__init__.py
clean_gml/utils/abs_path.py
clean_gml/utils/file_operations.py
clean_gml/utils/yml2dict.py
examples/__init__.py
examples/example_read.py
GML_cleaner-1.3.dist-info/LICENSE.txt
GML_cleaner-1.3.dist-info/METADATA
GML_cleaner-1.3.dist-info/WHEEL
GML_cleaner-1.3.dist-info/top_level.txt
GML_cleaner-1.3.dist-info/RECORD
