Metadata-Version: 2.1
Name: GML-cleaner
Version: 1.3
Summary: Gml cleaner is a python library for manupulating data and meta data in gml files.
Home-page: https://github.com/infralytics/gml_cleaner
Author: Wouter van Riel
Author-email: wouter.van.riel@infralytics.org
License: MIT
Platform: UNKNOWN
Classifier: Development Status :: 4 - Beta
Classifier: Intended Audience :: Developers
Classifier: License :: OSI Approved :: MIT License
Classifier: Natural Language :: English
Classifier: Operating System :: OS Independent
Classifier: Programming Language :: Python
Classifier: Programming Language :: Python :: 3.10
Classifier: Topic :: Scientific/Engineering :: GIS
Classifier: Topic :: Text Processing :: Markup :: XML
Requires-Dist: setuptools
